olapy/__init__.py
olapy/__main__.py
olapy/cli.py
olapy/core/__init__.py
olapy/core/mdx/__init__.py
olapy/core/mdx/executor/__init__.py
olapy/core/mdx/executor/cube_loader.py
olapy/core/mdx/executor/cube_loader_custom.py
olapy/core/mdx/executor/cube_loader_db.py
olapy/core/mdx/executor/execute.py
olapy/core/mdx/executor/lite_execute.py
olapy/core/mdx/executor/spark/__init__.py
olapy/core/mdx/executor/spark/cube_loader.py
olapy/core/mdx/executor/spark/execute.py
olapy/core/mdx/executor/utils.py
olapy/core/mdx/parser/__init__.py
olapy/core/mdx/parser/parse.py
olapy/core/mdx/tools/__init__.py
olapy/core/mdx/tools/config_file_parser.py
olapy/core/mdx/tools/connection.py
olapy/core/mdx/tools/olapy_config_file_parser.py
olapy/core/services/__init__.py
olapy/core/services/dict_discover_request_handler.py
olapy/core/services/dict_execute_request_handler.py
olapy/core/services/models.py
olapy/core/services/request_properties_models.py
olapy/core/services/spark/__init__.py
olapy/core/services/spark/xmla_discover_request_handler.py
olapy/core/services/spark/xmla_execute_request_handler.py
olapy/core/services/xmla.py
olapy/core/services/xmla_discover_request_handler.py
olapy/core/services/xmla_discover_request_utils.py
olapy/core/services/xmla_discover_xsds.py
olapy/core/services/xmla_execute_request_handler.py
olapy/core/services/xmla_execute_xsds.py
olapy/core/services/xmla_lib.py
olapy/etl/__init__.py
olapy/etl/etl.py
olapy/etl/etl_conf.yml
olapy/etl/input_dir/Geography.csv
olapy/etl/input_dir/Geography.txt
olapy/etl/input_dir/Product.csv
olapy/etl/input_dir/Product.txt
olapy/etl/input_dir/postgres_demo_dump.sql
olapy/etl/input_dir/sales_facts.csv
olapy/etl/input_dir/sales_facts.txt
olapy-0.8.2.dist-info/entry_points.txt
olapy-0.8.2.dist-info/LICENSE
olapy-0.8.2.dist-info/WHEEL
olapy-0.8.2.dist-info/METADATA
olapy-0.8.2.dist-info/RECORD
