Metadata-Version: 2.1
Name: olapy
Version: 0.8.2
Summary: OlaPy, an experimental OLAP engine based on Pandas
Home-page: https://github.com/abilian/olapy
Author: Abilian SAS
Requires-Python: >=3.8,<4
Classifier: Development Status :: 3 - Alpha
Classifier: Natural Language :: English
Classifier: Operating System :: OS Independent
Classifier: Programming Language :: Python
Classifier: Programming Language :: Python :: 2.7
Classifier: Programming Language :: Python :: 3
Classifier: Programming Language :: Python :: 3.10
Classifier: Programming Language :: Python :: 3.6
Classifier: Programming Language :: Python :: 3.7
Classifier: Programming Language :: Python :: 3.8
Classifier: Programming Language :: Python :: 3.9
Provides-Extra: etl
Provides-Extra: spark
Requires-Dist: attrs
Requires-Dist: awesome-slugify; extra == "etl"
Requires-Dist: bonobo-sqlalchemy (<0.6.1); extra == "etl"
Requires-Dist: bonobo; extra == "etl"
Requires-Dist: click
Requires-Dist: lxml
Requires-Dist: pandas
Requires-Dist: pyspark (<3); extra == "spark"
Requires-Dist: python-dotenv; extra == "etl"
Requires-Dist: pyyaml (>=4.2b1)
Requires-Dist: regex
Requires-Dist: spyne (>=2.13,<3.0)
Requires-Dist: sqlalchemy
Requires-Dist: typing
Requires-Dist: whistle (<1.0.1); extra == "etl"
Requires-Dist: xmlwitch
